setup.py
confy/__init__.py
confy/client.py
confy/api/__init__.py
confy/api/access.py
confy/api/config.py
confy/api/envs.py
confy/api/members.py
confy/api/orgs.py
confy/api/projects.py
confy/api/teams.py
confy/api/user.py
confy/error/__init__.py
confy/error/client_error.py
confy/http_client/__init__.py
confy/http_client/auth_handler.py
confy/http_client/error_handler.py
confy/http_client/request_handler.py
confy/http_client/response.py
confy/http_client/response_handler.py
confyio.egg-info/PKG-INFO
confyio.egg-info/SOURCES.txt
confyio.egg-info/dependency_links.txt
confyio.egg-info/requires.txt
confyio.egg-info/top_level.txt